{
  "id": "offer-mgyzn76h-4q9dm",
  "clientName": "ONZ Holdings",
  "title": "Lead Gen",
  "password": "5994471abb01112afcc18159f6cc74b4f511b99806da59b3caf5a9c173cacfc5",
  "htmlContent": "<!DOCTYPE html>\n<html lang=\"en\">\n<head>\n    <meta charset=\"UTF-8\">\n    <meta name=\"viewport\" content=\"width=device-width, initial-scale=1.0\">\n    <title>expandia | Quantum Satis Cleaning Interactive Proposal</title>\n    <script src=\"https://cdn.tailwindcss.com\"></script>\n    <link href=\"https://fonts.googleapis.com/css2?family=Inter:wght@400;500;600;700&display=swap\" rel=\"stylesheet\">\n    <style>\n        body {\n            font-family: 'Inter', sans-serif;\n            background-color: #f8fafc;\n        }\n        .service-card {\n            transition: all 0.3s ease;\n            cursor: pointer;\n        }\n        .service-card:hover {\n            transform: translateY(-5px);\n            box-shadow: 0 10px 15px -3px rgba(0, 0, 0, 0.1), 0 4px 6px -4px rgba(0, 0, 0, 0.1);\n        }\n        @media print {\n            body {\n                padding: 0;\n                margin: 0;\n            }\n            header, #welcome-screen, #back-to-services, .print-hide, footer {\n                display: none !important;\n            }\n            #demo-view {\n                display: block !important;\n            }\n            .printable-area {\n                box-shadow: none !important;\n                border: none !important;\n            }\n        }\n    </style>\n</head>\n<body class=\"p-4 md:p-8\">\n    <div class=\"max-w-7xl mx-auto bg-white rounded-2xl shadow-lg overflow-hidden printable-area\">\n        <!-- Header -->\n        <header class=\"bg-[#18182f] text-white p-6 flex flex-col md:flex-row justify-between items-center\">\n            <div class=\"flex items-center space-x-4\">\n                <!-- Expandia Logo -->\n                <div class=\"text-2xl font-bold tracking-wider text-white\">\n                    <span class=\"text-[#e0a82e]\">e</span>xpandia\n                </div>\n                <span class=\"text-2xl font-thin text-gray-500\">|</span>\n                <!-- Quantum Satis Cleaning Text Logo -->\n                <div class=\"flex items-center space-x-2\">\n                     <span class=\"text-xl font-semibold\">Quantum Satis Cleaning</span>\n                </div>\n            </div>\n            <div class=\"text-center md:text-right mt-4 md:mt-0\">\n                <h1 class=\"text-xl md:text-2xl font-bold\">Client Acquisition Program</h1>\n                <p class=\"text-sm text-gray-300\">Zürich (Priority) → Schwyz → St. Gallen</p>\n            </div>\n        </header>\n\n        <!-- Main Content Area -->\n        <main class=\"p-6 md:p-8\">\n            <!-- Welcome Screen (Visible by default) -->\n            <div id=\"welcome-screen\">\n                <!-- Project Goal Section -->\n                <div class=\"mb-12 p-6 bg-yellow-50 border border-yellow-200 rounded-xl text-center\">\n                    <h2 class=\"text-2xl font-bold text-gray-800 mb-2\">Objective</h2>\n                    <p class=\"text-gray-700 max-w-4xl mx-auto\">\n                        Our goal is to achieve ≈500 service hours/month in the medium term through a combined B2B and B2C strategy. For B2B, we will maintain structured outreach to ≈200 companies per month. For B2C, we will run always-on digital advertising to generate steady residential and small commercial demand, starting with Canton Zürich.\n                    </p>\n                </div>\n\n                <!-- Program Details Section -->\n                <div class=\"mb-12\">\n                    <h2 class=\"text-3xl font-bold text-gray-800 text-center\">Program Packages</h2>\n                    <p class=\"mt-2 text-lg text-gray-600 text-center\">Choose the stream that best fits your growth stage, or combine them for accelerated results.</p>\n                    <div class=\"mt-8 grid grid-cols-1 md:grid-cols-2 lg:grid-cols-3 gap-6\">\n                        <div class=\"service-card bg-gray-50 border rounded-xl p-6 lg:col-span-1\" data-target=\"b2c-packages\">\n                            <h4 class=\"text-xl font-bold text-gray-800\">A) B2C Packages</h4>\n                            <p class=\"mt-2 text-sm text-gray-700\">\"Always-On Digital Demand\" for residential and small commercial clients via Google, Meta & TikTok.</p>\n                            <div class=\"mt-4 text-right\">\n                                <span class=\"text-sm font-semibold text-gray-600\">View B2C Details &rarr;</span>\n                            </div>\n                        </div>\n                        <div class=\"service-card bg-gray-50 border rounded-xl p-6 lg:col-span-1\" data-target=\"b2b-packages\">\n                            <h4 class=\"text-xl font-bold text-gray-800\">B) B2B Packages</h4>\n                            <p class=\"mt-2 text-sm text-gray-700\">\"Structured Corporate Acquisition\" targeting offices, property managers, clinics, and more.</p>\n                            <div class=\"mt-4 text-right\">\n                                <span class=\"text-sm font-semibold text-gray-600\">View B2B Details &rarr;</span>\n                            </div>\n                        </div>\n                         <div class=\"service-card bg-yellow-50 border-2 border-[#e0a82e] rounded-xl p-6 shadow-lg md:col-span-2 lg:col-span-1\" data-target=\"combo-packages\">\n                             <h4 class=\"text-xl font-bold text-yellow-900\">C) Combo Packages</h4>\n                            <p class=\"mt-2 text-sm text-yellow-800\">\"Accelerated Growth\" through full integration of B2C and B2B workstreams under one unified plan.</p>\n                            <div class=\"mt-4 text-right\">\n                                <span class=\"text-sm font-semibold text-yellow-700\">View Combo Details &rarr;</span>\n                            </div>\n                        </div>\n                    </div>\n                </div>\n\n                <!-- Example Workflow Section -->\n                <div class=\"mb-12\">\n                    <h2 class=\"text-3xl font-bold text-gray-800 text-center\">Example Workflow & Playbook</h2>\n                    <p class=\"mt-2 text-lg text-gray-600 text-center\">Concrete examples of ads, emails, and scripts we'll use for your campaign.</p>\n                    <div class=\"mt-8 max-w-2xl mx-auto\">\n                        <div class=\"service-card bg-blue-50 border-2 border-blue-400 rounded-xl p-6 shadow-lg\" data-target=\"example-workflow\">\n                            <h4 class=\"text-xl font-bold text-blue-900\">View B2C & B2B Campaign Examples</h4>\n                            <p class=\"mt-2 text-sm text-blue-800\">See ready-to-use ad copy, outreach emails, call scripts, and reporting formats tailored for the Zürich market.</p>\n                            <div class=\"mt-4 text-right\">\n                                <span class=\"text-sm font-semibold text-blue-700\">View Playbook Examples &rarr;</span>\n                            </div>\n                        </div>\n                    </div>\n                </div>\n\n                 <!-- Other Details Section -->\n                <div class=\"mb-12\">\n                    <h2 class=\"text-3xl font-bold text-gray-800 text-center\">Add-Ons & Project Details</h2>\n                    <p class=\"mt-2 text-lg text-gray-600 text-center\">Enhance your package and understand our delivery process.</p>\n                    <div class=\"mt-8 grid grid-cols-1 md:grid-cols-2 gap-6\">\n                        <div class=\"service-card bg-gray-50 border rounded-xl p-6\" data-target=\"add-ons\">\n                            <h4 class=\"text-xl font-bold text-gray-800\">Optional Add-Ons</h4>\n                            <p class=\"mt-2 text-sm text-gray-700\">Customize your program with services like Meeting Moderation, CRM Setup, LinkedIn Management, and more.</p>\n                            <div class=\"mt-4 text-right\">\n                                <span class=\"text-sm font-semibold text-gray-600\">View All Add-Ons &rarr;</span>\n                            </div>\n                        </div>\n                        <div class=\"service-card bg-gray-50 border rounded-xl p-6\" data-target=\"delivery-terms\">\n                            <h4 class=\"text-xl font-bold text-gray-800\">Delivery, SLA & Terms</h4>\n                            <p class=\"mt-2 text-sm text-gray-700\">Our approach to kick-off, reporting, service level agreements, and contract terms.</p>\n                            <div class=\"mt-4 text-right\">\n                                <span class=\"text-sm font-semibold text-gray-600\">View Delivery Details &rarr;</span>\n                            </div>\n                        </div>\n                    </div>\n                </div>\n            </div>\n\n            <!-- Demo View (Hidden by default) -->\n            <div id=\"demo-view\" class=\"hidden\">\n                <div class=\"flex justify-between items-center mb-6\">\n                    <button id=\"back-to-services\" class=\"inline-flex items-center px-4 py-2 border border-transparent text-sm font-medium rounded-md shadow-sm text-white bg-gray-600 hover:bg-gray-700 focus:outline-none focus:ring-2 focus:ring-offset-2 focus:ring-gray-500\">\n                        <svg class=\"w-5 h-5 mr-2\" xmlns=\"http://www.w3.org/2000/svg\" viewBox=\"0 0 20 20\" fill=\"currentColor\"><path fill-rule=\"evenodd\" d=\"M12.707 5.293a1 1 0 010 1.414L9.414 10l3.293 3.293a1 1 0 01-1.414 1.414l-4-4a1 1 0 010-1.414l4-4a1 1 0 011.414 0z\" clip-rule=\"evenodd\" /></svg>\n                        Back to Overview\n                    </button>\n                    <button onclick=\"window.print()\" class=\"print-hide inline-flex items-center px-4 py-2 border border-gray-300 text-sm font-medium rounded-md shadow-sm text-gray-700 bg-white hover:bg-gray-50\">\n                         <svg class=\"w-5 h-5 mr-2 text-gray-500\" xmlns=\"http://www.w3.org/2000/svg\" viewBox=\"0 0 20 20\" fill=\"currentColor\"><path fill-rule=\"evenodd\" d=\"M5 4v3H4a2 2 0 00-2 2v6a2 2 0 002 2h12a2 2 0 002-2V9a2 2 0 00-2-2h-1V4a2 2 0 00-2-2H7a2 2 0 00-2 2zm8 0H7v3h6V4zm0 8H7v4h6v-4z\" clip-rule=\"evenodd\" /></svg>\n                        Print / Save as PDF\n                    </button>\n                </div>\n                <div id=\"demo-content-wrapper\"></div>\n            </div>\n        </main>\n\n        <!-- Footer -->\n        <footer class=\"bg-gray-100 border-t p-6 text-center text-gray-600 text-sm\">\n            <p class=\"font-semibold\">Expandia.ch — by Remova Inc, DE, USA</p>\n            <div class=\"mt-2 space-x-4\">\n                <a href=\"mailto:oguz@expandia.ch\" class=\"hover:underline\">oguz@expandia.ch</a>\n                 <span>&bull;</span>\n                <a href=\"tel:+41778107264\" class=\"hover:underline\">+41 77 810 72 64</a>\n            </div>\n            <p class=\"mt-2\">Prepared by Oguz (Ozzy) Ocak</p>\n        </footer>\n    </div>\n\n    <!-- Demo Content Templates -->\n    <template id=\"b2c-packages\">\n        <div class=\"space-y-8 printable-area\">\n            <div>\n                <h2 class=\"text-3xl font-bold text-gray-800\">A) B2C Packages — “Always-On Digital Demand”</h2>\n                <p class=\"mt-2 text-lg text-gray-600\">Generate steady residential and small commercial demand in Zürich.</p>\n            </div>\n            <div class=\"p-6 bg-gray-50 rounded-xl border\">\n                <h3 class=\"text-xl font-semibold text-gray-800 mb-4\">Scope (Applies to all B2C terms)</h3>\n                <ul class=\"space-y-2 list-disc list-inside text-gray-700\">\n                    <li><strong>Google Ads (Search/Maps/P-Max):</strong> Setup, optimization, and management.</li>\n                    <li><strong>Google Business Profile (GMB):</strong> Profile optimization, offers/posts, review guidance.</li>\n                    <li><strong>Meta Ads (Facebook/Instagram):</strong> Creative variants and A/B testing.</li>\n                    <li><strong>TikTok Ads:</strong> Short-form concepting and campaign management.</li>\n                    <li><strong>Local Listings:</strong> Management on local.ch, search.ch, etc.</li>\n                    <li><strong>Tracking & Analytics:</strong> GA4 setup, conversion goals, call/form tracking; weekly optimization & monthly reports.</li>\n                    <li><strong>Creatives:</strong> 3 visual/video variants per month (copy + light edits).</li>\n                    <li><strong>Strategy Time:</strong> Up to 60 minutes/month (DE/EN).</li>\n                </ul>\n                <p class=\"text-sm text-gray-500 mt-4\">Note: Media spend (suggested 1,000–1,500 CHF/month) is paid directly by the client.</p>\n            </div>\n            <div class=\"p-8 bg-blue-50 rounded-2xl border\">\n                <h3 class=\"text-2xl font-semibold text-blue-900 mb-4 text-center\">B2C Package Pricing</h3>\n                <div class=\"grid grid-cols-1 md:grid-cols-3 gap-6 mt-6\">\n                    <div class=\"bg-white rounded-lg border p-6 text-center flex flex-col\">\n                        <h4 class=\"font-bold text-lg\">3-Month Package</h4>\n                        <p class=\"text-4xl font-bold my-4\">4,200 <span class=\"text-lg font-normal\">CHF</span></p>\n                        <p class=\"text-gray-500 flex-grow\">(effective ≈ 1,400/month)</p>\n                    </div>\n                    <div class=\"bg-white rounded-lg border-2 border-blue-600 p-6 text-center flex flex-col ring-4 ring-blue-100\">\n                        <h4 class=\"font-bold text-lg text-blue-600\">6-Month Package</h4>\n                        <p class=\"text-4xl font-bold my-4\">7,800 <span class=\"text-lg font-normal\">CHF</span></p>\n                        <p class=\"text-gray-500 flex-grow\">(effective ≈ 1,300/month)</p>\n                    </div>\n                    <div class=\"bg-white rounded-lg border p-6 text-center flex flex-col\">\n                        <h4 class=\"font-bold text-lg\">12-Month Package</h4>\n                        <p class=\"text-4xl font-bold my-4\">14,400 <span class=\"text-lg font-normal\">CHF</span></p>\n                        <p class=\"text-gray-500 flex-grow\">(effective ≈ 1,200/month)</p>\n                    </div>\n                </div>\n                <p class=\"text-center text-sm text-gray-600 mt-6\"><strong>Payment Plan:</strong> 50% upfront, 50% at the mid-point of the term for all packages.</p>\n            </div>\n        </div>\n    </template>\n    \n    <template id=\"b2b-packages\">\n        <div class=\"space-y-8 printable-area\">\n            <div>\n                <h2 class=\"text-3xl font-bold text-gray-800\">B) B2B Packages — “Structured Corporate Acquisition”</h2>\n                <p class=\"mt-2 text-lg text-gray-600\">Systematic outreach to high-value corporate clients in Canton Zürich.</p>\n            </div>\n            <div class=\"p-6 bg-gray-50 rounded-xl border\">\n                <h3 class=\"text-xl font-semibold text-gray-800 mb-4\">Scope (Applies to all B2B terms)</h3>\n                <ul class=\"space-y-2 list-disc list-inside text-gray-700\">\n                    <li><strong>Targeting:</strong> Offices, schools, property/facility managers, clinics, light manufacturing, etc.</li>\n                    <li><strong>Monthly Contact Volume:</strong> ≈200 companies (German-first, English as needed) via email, LinkedIn, and compliant calls.</li>\n                    <li><strong>Records & Compliance:</strong> All interactions logged in CRM; calendar invites for confirmed meetings; DSG/GDPR & UWG compliant.</li>\n                    <li><strong>Content:</strong> Concise outreach emails + a 1–2 page service overview PDF.</li>\n                    <li><strong>Reporting:</strong> Weekly summary and monthly detailed report (contacts reached, responses, scheduled meetings).</li>\n                </ul>\n            </div>\n            <div class=\"p-8 bg-blue-50 rounded-2xl border\">\n                <h3 class=\"text-2xl font-semibold text-blue-900 mb-4 text-center\">B2B Package Pricing</h3>\n                <div class=\"grid grid-cols-1 md:grid-cols-3 gap-6 mt-6\">\n                    <div class=\"bg-white rounded-lg border p-6 text-center flex flex-col\">\n                        <h4 class=\"font-bold text-lg\">3-Month Package</h4>\n                        <p class=\"text-4xl font-bold my-4\">3,780 <span class=\"text-lg font-normal\">CHF</span></p>\n                        <p class=\"text-gray-500 flex-grow\">(effective ≈ 1,260/month)</p>\n                    </div>\n                    <div class=\"bg-white rounded-lg border-2 border-blue-600 p-6 text-center flex flex-col ring-4 ring-blue-100\">\n                        <h4 class=\"font-bold text-lg text-blue-600\">6-Month Package</h4>\n                        <p class=\"text-4xl font-bold my-4\">6,840 <span class=\"text-lg font-normal\">CHF</span></p>\n                        <p class=\"text-gray-500 flex-grow\">(effective ≈ 1,140/month)</p>\n                    </div>\n                    <div class=\"bg-white rounded-lg border p-6 text-center flex flex-col\">\n                        <h4 class=\"font-bold text-lg\">12-Month Package</h4>\n                        <p class=\"text-4xl font-bold my-4\">12,960 <span class=\"text-lg font-normal\">CHF</span></p>\n                        <p class=\"text-gray-500 flex-grow\">(effective ≈ 1,080/month)</p>\n                    </div>\n                </div>\n                <p class=\"text-center text-sm text-gray-600 mt-6\"><strong>Payment Plan:</strong> 50% upfront, 50% at the mid-point of the term for all packages.</p>\n            </div>\n        </div>\n    </template>\n    \n    <template id=\"combo-packages\">\n        <div class=\"space-y-8 printable-area\">\n            <div>\n                <h2 class=\"text-3xl font-bold text-gray-800\">C) Combo Packages — “Accelerated Growth”</h2>\n                <p class=\"mt-2 text-lg text-gray-600\">The ultimate solution integrating both B2C and B2B streams for maximum market impact.</p>\n            </div>\n            <div class=\"p-6 bg-gray-50 rounded-xl border\">\n                <h3 class=\"text-xl font-semibold text-gray-800 mb-4\">Scope (Applies to all Combo terms)</h3>\n                <ul class=\"space-y-2 list-disc list-inside text-gray-700\">\n                    <li><strong>Full Integration:</strong> Complete B2C and B2B workstreams under one unified plan.</li>\n                    <li><strong>Unified Reporting:</strong> One monthly report combining digital demand and corporate outreach results.</li>\n                    <li><strong>Message Alignment:</strong> Consistent offers across channels and cross-learning (using B2C insights to refine B2B messaging).</li>\n                </ul>\n            </div>\n            <div class=\"p-8 bg-yellow-50 rounded-2xl border\">\n                <h3 class=\"text-2xl font-semibold text-yellow-900 mb-4 text-center\">Combo Package Pricing</h3>\n                <div class=\"grid grid-cols-1 md:grid-cols-3 gap-6 mt-6\">\n                    <div class=\"bg-white rounded-lg border p-6 text-center flex flex-col\">\n                        <h4 class=\"font-bold text-lg\">3-Month Package</h4>\n                        <p class=\"text-4xl font-bold my-4\">5,760 <span class=\"text-lg font-normal\">CHF</span></p>\n                        <p class=\"text-gray-500 flex-grow\">(effective ≈ 1,920/month)</p>\n                    </div>\n                    <div class=\"bg-white rounded-lg border-2 border-yellow-600 p-6 text-center flex flex-col ring-4 ring-yellow-100\">\n                        <h4 class=\"font-bold text-lg text-yellow-600\">6-Month Package</h4>\n                        <p class=\"text-4xl font-bold my-4\">10,800 <span class=\"text-lg font-normal\">CHF</span></p>\n                        <p class=\"text-gray-500 flex-grow\">(effective ≈ 1,800/month)</p>\n                    </div>\n                    <div class=\"bg-white rounded-lg border p-6 text-center flex flex-col\">\n                        <h4 class=\"font-bold text-lg\">12-Month Package</h4>\n                        <p class=\"text-4xl font-bold my-4\">20,160 <span class=\"text-lg font-normal\">CHF</span></p>\n                        <p class=\"text-gray-500 flex-grow\">(effective ≈ 1,680/month)</p>\n                    </div>\n                </div>\n                <p class=\"text-center text-sm text-gray-600 mt-6\"><strong>Payment Plan:</strong> 50% upfront, 50% at the mid-point of the term for all packages.</p>\n            </div>\n        </div>\n    </template>\n    \n    <template id=\"add-ons\">\n        <div class=\"space-y-8 printable-area\">\n            <div>\n                <h2 class=\"text-3xl font-bold text-gray-800\">Optional Add-Ons</h2>\n                <p class=\"mt-2 text-lg text-gray-600\">Enhance your chosen package with these optional, separately billed services.</p>\n            </div>\n            <div class=\"p-6 bg-gray-50 rounded-xl border\">\n                <ul class=\"divide-y divide-gray-200\">\n                    <li class=\"py-4 flex justify-between items-center\">\n                        <div>\n                            <p class=\"font-semibold\">Meeting Moderation (DE/EN)</p>\n                            <p class=\"text-sm text-gray-600\">We host online meetings, deliver a written summary and action points.</p>\n                        </div>\n                        <p class=\"font-semibold text-right\">+300 CHF / month</p>\n                    </li>\n                    <li class=\"py-4 flex justify-between items-center\">\n                        <div>\n                            <p class=\"font-semibold\">Cold Calling (Native DE)</p>\n                            <p class=\"text-sm text-gray-600\">Appointment-oriented compliant calling on approved lists (min. 200 min block).</p>\n                        </div>\n                        <p class=\"font-semibold text-right\">1.50 CHF / minute</p>\n                    </li>\n                    <li class=\"py-4 flex justify-between items-center\">\n                        <div>\n                            <p class=\"font-semibold\">Additional Target Accounts (B2B)</p>\n                            <p class=\"text-sm text-gray-600\">Research & add incremental companies to your outreach list.</p>\n                        </div>\n                        <p class=\"font-semibold text-right\">0.60 CHF / account</p>\n                    </li>\n                    <li class=\"py-4 flex justify-between items-center\">\n                        <div>\n                            <p class=\"font-semibold\">CRM Setup & Integrations (HubSpot/Pipedrive)</p>\n                            <p class=\"text-sm text-gray-600\">Fields, automations, and team onboarding.</p>\n                        </div>\n                        <p class=\"font-semibold text-right\">3,000 CHF (one-time)</p>\n                    </li>\n                    <li class=\"py-4 flex justify-between items-center\">\n                        <div>\n                            <p class=\"font-semibold\">CRM Maintenance & Monitoring</p>\n                            <p class=\"text-sm text-gray-600\">Data hygiene, integration checks, and dashboards.</p>\n                        </div>\n                        <p class=\"font-semibold text-right\">600 CHF / month</p>\n                    </li>\n                    <li class=\"py-4 flex justify-between items-center\">\n                        <div>\n                            <p class=\"font-semibold\">Company LinkedIn Management</p>\n                            <p class=\"text-sm text-gray-600\">8 posts/month + direct message triage.</p>\n                        </div>\n                        <p class=\"font-semibold text-right\">1,200 CHF / month</p>\n                    </li>\n                    <li class=\"py-4 flex justify-between items-center\">\n                        <div>\n                            <p class=\"font-semibold\">Executive LinkedIn Management</p>\n                            <p class=\"text-sm text-gray-600\">Up to 2,500 connection outreach & messaging.</p>\n                        </div>\n                        <p class=\"font-semibold text-right\">800 CHF / month</p>\n                    </li>\n                    <li class=\"py-4 flex justify-between items-center\">\n                        <div>\n                            <p class=\"font-semibold\">Bulk Email Infrastructure</p>\n                            <p class=\"text-sm text-gray-600\">Sending infrastructure, compliance rules, basic templates.</p>\n                        </div>\n                        <p class=\"font-semibold text-right\">350 CHF / month</p>\n                    </li>\n                    <li class=\"py-4 flex justify-between items-center\">\n                        <div>\n                            <p class=\"font-semibold\">Advanced GMB Optimization</p>\n                            <p class=\"text-sm text-gray-600\">Categories, service areas, automated Q&A, offer posts.</p>\n                        </div>\n                        <p class=\"font-semibold text-right\">450 CHF (one-time)</p>\n                    </li>\n                    <li class=\"py-4 flex justify-between items-center\">\n                        <div>\n                            <p class=\"font-semibold\">Bi-lingual Micro-Landing Page</p>\n                            <p class=\"text-sm text-gray-600\">No-code draft with professional DE/EN copy.</p>\n                        </div>\n                        <p class=\"font-semibold text-right\">900 CHF (one-time)</p>\n                    </li>\n                </ul>\n            </div>\n        </div>\n    </template>\n\n    <template id=\"delivery-terms\">\n        <div class=\"space-y-8 printable-area\">\n            <div>\n                <h2 class=\"text-3xl font-bold text-gray-800\">Delivery Approach, SLA & Contract Terms</h2>\n                <p class=\"mt-2 text-lg text-gray-600\">Our commitment to a transparent, compliant, and effective partnership.</p>\n            </div>\n            <div class=\"grid grid-cols-1 lg:grid-cols-2 gap-8\">\n                <div class=\"p-6 bg-gray-50 rounded-xl border\">\n                    <h3 class=\"text-xl font-semibold text-gray-800 mb-4\">Delivery Approach</h3>\n                    <div class=\"space-y-4\">\n                        <div>\n                            <h4 class=\"font-semibold\">Kick-off (Weeks 1–2)</h4>\n                            <ul class=\"list-disc list-inside text-sm text-gray-600 mt-1\">\n                                <li>Goals & targeting alignment (60–90 min session).</li>\n                                <li>Tracking/label setup (GA4, GMB, conversions).</li>\n                                <li>B2B target list & outreach templates approval.</li>\n                                <li>Launch initial B2C creatives and first B2B contact set.</li>\n                            </ul>\n                        </div>\n                        <div>\n                            <h4 class=\"font-semibold\">Ongoing (Monthly)</h4>\n                            <ul class=\"list-disc list-inside text-sm text-gray-600 mt-1\">\n                                <li>Weekly updates (key actions and highlights).</li>\n                                <li>Monthly detailed report (metrics, insights, next-month focus).</li>\n                            </ul>\n                        </div>\n                    </div>\n                </div>\n                <div class=\"p-6 bg-gray-50 rounded-xl border\">\n                    <h3 class=\"text-xl font-semibold text-gray-800 mb-4\">SLA & Contract Terms</h3>\n                    <div class=\"space-y-4\">\n                        <div>\n                            <h4 class=\"font-semibold\">Service Level Agreement (SLA)</h4>\n                            <ul class=\"list-disc list-inside text-sm text-gray-600 mt-1\">\n                                <li>Responses within 24 business hours; same-day for critical issues.</li>\n                                <li>Compliance-first approach: DSG/GDPR, UWG, and local rules.</li>\n                                <li>Transparent records and clear opt-out management.</li>\n                            </ul>\n                        </div>\n                        <div>\n                            <h4 class=\"font-semibold\">Contract & Terms</h4>\n                             <ul class=\"list-disc list-inside text-sm text-gray-600 mt-1\">\n                                <li><strong>Package Terms:</strong> 3 / 6 / 12 months (single fee per term).</li>\n                                <li><strong>Payment:</strong> 50% upfront + 50% at mid-term.</li>\n                                <li><strong>Media Budgets:</strong> Paid directly by client.</li>\n                                <li><strong>Geography:</strong> Start with Zürich, then expand to Schwyz and St. Gallen.</li>\n                                <li>Confidentiality/NDA included in the agreement.</li>\n                            </ul>\n                        </div>\n                    </div>\n                </div>\n            </div>\n        </div>\n    </template>\n\n    <template id=\"example-workflow\">\n        <div class=\"space-y-8 printable-area\">\n            <div>\n                <h2 class=\"text-3xl font-bold text-gray-800\">Example Workflow & Playbook</h2>\n                <p class=\"mt-2 text-lg text-gray-600\">Absolutely—here are concrete, ready-to-use examples for both B2C and B2B tailored to Zürich (DE-first, EN optional).</p>\n            </div>\n            <div class=\"grid grid-cols-1 lg:grid-cols-2 gap-8\">\n                <!-- B2C Column -->\n                <div class=\"space-y-6\">\n                    <h3 class=\"text-2xl font-bold text-gray-800 border-b pb-2\">A) B2C Examples (Residential)</h3>\n                    <div class=\"p-4 bg-gray-50 rounded-lg border\">\n                        <h4 class=\"font-semibold\">1) Google Search Ads (DE)</h4>\n                        <p class=\"text-sm font-medium mt-2\">Theme: End-of-tenancy / Deep cleaning</p>\n                        <p class=\"text-xs text-gray-600\">Keywords: wohnungsreinigung zürich, umzugsreinigung mit abnahme...</p>\n                        <div class=\"mt-2 p-3 bg-white border rounded\">\n                            <p class=\"font-semibold text-blue-600 text-sm\">Umzugsreinigung in Zürich – Fix Termin, Fix Preis</p>\n                            <p class=\"text-xs\">Endreinigung mit Abnahme-Garantie. Schnellangebot in 15 Min. Versicherte Teams. Heute rufen.</p>\n                        </div>\n                    </div>\n                    <div class=\"p-4 bg-gray-50 rounded-lg border\">\n                        <h4 class=\"font-semibold\">2) Google Business Profile (GMB) Post</h4>\n                        <p class=\"text-sm mt-2\">“Weekend Deep Clean – 10% off for new Zürich customers” (validity Fri–Sun).</p>\n                    </div>\n                    <div class=\"p-4 bg-gray-50 rounded-lg border\">\n                        <h4 class=\"font-semibold\">3) Meta / TikTok Concept</h4>\n                        <p class=\"text-sm mt-2\">60-sec Reel: “From Mess to Fresh” – fast-cut before/after of a kitchen + CTA “Free quick quote in 15 minutes—tap ‘Send Message’.”</p>\n                    </div>\n                    <div class=\"p-4 bg-gray-50 rounded-lg border\">\n                        <h4 class=\"font-semibold\">4) Offers & Landing Micro-structure</h4>\n                         <p class=\"text-sm mt-2\">Headline: Trusted Cleaning in Zürich—Transparent Prices, Insured Teams. Blocks: Service menu, Instant quote form, Reviews, Checklist, FAQ.</p>\n                    </div>\n                </div>\n                <!-- B2B Column -->\n                <div class=\"space-y-6\">\n                    <h3 class=\"text-2xl font-bold text-gray-800 border-b pb-2\">B) B2B Examples (Corporate)</h3>\n                    <div class=\"p-4 bg-gray-50 rounded-lg border\">\n                        <h4 class=\"font-semibold\">1) Ideal Customer Profiles (ICPs)</h4>\n                        <ul class=\"list-disc list-inside text-sm text-gray-600 mt-1\">\n                            <li>Property Managers / Hausverwaltungen</li>\n                            <li>Kinderkrippen / Schulen</li>\n                            <li>Medical / Dental Clinics</li>\n                        </ul>\n                    </div>\n                    <div class=\"p-4 bg-gray-50 rounded-lg border\">\n                        <h4 class=\"font-semibold\">2) Outreach Email – German (Property Manager)</h4>\n                        <div class=\"mt-2 p-3 bg-white border rounded text-xs\">\n                            <p class=\"font-semibold\">Subject: Unterhaltsreinigung für Ihre Liegenschaften in Zürich</p>\n                            <p class=\"mt-1\">Guten Tag Frau/Herr {{Nachname}},<br>wir unterstützen Hausverwaltungen in Zürich mit zuverlässiger Unterhaltsreinigung... Gern prüfe ich eine Ihrer Liegenschaften diese Woche vor Ort (kostenlos)... Passt Ihnen {{Datum/Zeitraum}}?</p>\n                        </div>\n                    </div>\n                    <div class=\"p-4 bg-gray-50 rounded-lg border\">\n                        <h4 class=\"font-semibold\">3) Call Opener (DE) – Gatekeeper-friendly</h4>\n                        <p class=\"text-sm mt-2 italic\">“Schönen guten Tag, hier ist Anna von Quantum Satis Cleaning... Wer kümmert sich bei Ihnen um die Reinigungsdienstleister, damit ich eine kurze Begehung vorschlagen kann?”</p>\n                    </div>\n                     <div class=\"p-4 bg-gray-50 rounded-lg border\">\n                        <h4 class=\"font-semibold\">4) Qualification Questions</h4>\n                         <ul class=\"list-disc list-inside text-sm text-gray-600 mt-1\">\n                            <li>How many sites/units? Frequency?</li>\n                            <li>Current challenges (no-shows, quality)?</li>\n                         </ul>\n                    </div>\n                </div>\n            </div>\n             <!-- Reporting & Handling -->\n            <div class=\"mt-8 pt-8 border-t\">\n                <h3 class=\"text-2xl font-bold text-gray-800 text-center mb-6\">Reporting & Objection Handling Examples</h3>\n                <div class=\"grid grid-cols-1 md:grid-cols-2 gap-8\">\n                     <div class=\"p-4 bg-gray-50 rounded-lg border\">\n                        <h4 class=\"font-semibold\">Reporting Example (Weekly Note)</h4>\n                        <p class=\"text-sm mt-2\"><strong>B2C:</strong> 73 inquiries this week. Top driver: “Umzugsreinigung Zürich”. Recommendation: increase Maps placements by +20%.</p>\n                        <p class=\"text-sm mt-1\"><strong>B2B:</strong> 205 companies contacted, 18 positive replies, 6 site-visit windows proposed. Most responsive: property managers in Kreis 3/4.</p>\n                    </div>\n                     <div class=\"p-4 bg-gray-50 rounded-lg border\">\n                        <h4 class=\"font-semibold\">Objection Handling Example</h4>\n                        <p class=\"text-sm mt-2\"><strong>\"We already have a cleaner.\"</strong></p>\n                        <p class=\"text-sm text-gray-600 mt-1\">\"Totally fine—many clients do. We usually start with a single site or a seasonal deep clean to compare quality and reliability without disrupting current routines.\"</p>\n                    </div>\n                </div>\n            </div>\n        </div>\n    </template>\n    \n    <script>\n        document.addEventListener('DOMContentLoaded', () => {\n            const welcomeScreen = document.getElementById('welcome-screen');\n            const demoView = document.getElementById('demo-view');\n            const demoContentWrapper = document.getElementById('demo-content-wrapper');\n            const backButton = document.getElementById('back-to-services');\n            \n            document.querySelectorAll('.service-card').forEach(card => {\n                card.addEventListener('click', (e) => {\n                    const targetId = card.dataset.target;\n                    if (targetId) {\n                        e.preventDefault();\n                        const contentTemplate = document.getElementById(targetId);\n\n                        if (contentTemplate) {\n                            welcomeScreen.classList.add('hidden');\n                            demoView.classList.remove('hidden');\n                            demoContentWrapper.innerHTML = contentTemplate.innerHTML;\n                            window.scrollTo(0, 0);\n                        }\n                    }\n                });\n            });\n\n            if(demoView && backButton) {\n                backButton.addEventListener('click', () => {\n                    demoView.classList.add('hidden');\n                    welcomeScreen.classList.remove('hidden');\n                    demoContentWrapper.innerHTML = ''; // Clear content\n                    window.scrollTo(0, 0);\n                });\n            }\n        });\n    </script>\n</body>\n</html>\n\n\n",
  "createdAt": "2025-10-20T10:24:26.153Z",
  "updatedAt": "2025-10-20T10:25:09.597Z"
}